cashflow/VERSION
cashflow/__init__.py
cashflow/budget/__init__.py
cashflow/budget/cli.py
cashflow/budget/processor.py
cashflow/days/main.py
cashflow/statement/__init__.py
cashflow/statement/budget.py
cashflow/statement/category.py
cashflow/statement/cli.py
cashflow/statement/processor.py
cashflow/statement/vocab.py
cashflow_manager-0.6.2.dist-info/METADATA
cashflow_manager-0.6.2.dist-info/WHEEL
cashflow_manager-0.6.2.dist-info/entry_points.txt
cashflow_manager-0.6.2.dist-info/RECORD
